adminlte/__init__.py
adminlte/adminlte.py
adminlte/apps.py
adminlte/forms.py
adminlte/urls.py
adminlte/utils.py
adminlte/static/adminLTE/css/AdminLTE.css
adminlte/static/adminLTE/css/AdminLTE.min.css
adminlte/static/adminLTE/css/google_fonts.css
adminlte/static/adminLTE/css/skins/_all-skins.css
adminlte/static/adminLTE/css/skins/_all-skins.min.css
adminlte/static/adminLTE/css/skins/skin-black-light.css
adminlte/static/adminLTE/css/skins/skin-black-light.min.css
adminlte/static/adminLTE/css/skins/skin-black.css
adminlte/static/adminLTE/css/skins/skin-black.min.css
adminlte/static/adminLTE/css/skins/skin-blue-light.css
adminlte/static/adminLTE/css/skins/skin-blue-light.min.css
adminlte/static/adminLTE/css/skins/skin-blue.css
adminlte/static/adminLTE/css/skins/skin-blue.min.css
adminlte/static/adminLTE/css/skins/skin-green-light.css
adminlte/static/adminLTE/css/skins/skin-green-light.min.css
adminlte/static/adminLTE/css/skins/skin-green.css
adminlte/static/adminLTE/css/skins/skin-green.min.css
adminlte/static/adminLTE/css/skins/skin-purple-light.css
adminlte/static/adminLTE/css/skins/skin-purple-light.min.css
adminlte/static/adminLTE/css/skins/skin-purple.css
adminlte/static/adminLTE/css/skins/skin-purple.min.css
adminlte/static/adminLTE/css/skins/skin-red-light.css
adminlte/static/adminLTE/css/skins/skin-red-light.min.css
adminlte/static/adminLTE/css/skins/skin-red.css
adminlte/static/adminLTE/css/skins/skin-red.min.css
adminlte/static/adminLTE/css/skins/skin-yellow-light.css
adminlte/static/adminLTE/css/skins/skin-yellow-light.min.css
adminlte/static/adminLTE/css/skins/skin-yellow.css
adminlte/static/adminLTE/css/skins/skin-yellow.min.css
adminlte/static/adminLTE/img/avatar.png
adminlte/static/adminLTE/img/avatar04.png
adminlte/static/adminLTE/img/avatar2.png
adminlte/static/adminLTE/img/avatar3.png
adminlte/static/adminLTE/img/avatar5.png
adminlte/static/adminLTE/img/boxed-bg.jpg
adminlte/static/adminLTE/img/boxed-bg.png
django_adminlte_admin-0.6.1.dist-info/DESCRIPTION.rst
django_adminlte_admin-0.6.1.dist-info/METADATA
django_adminlte_admin-0.6.1.dist-info/RECORD
django_adminlte_admin-0.6.1.dist-info/WHEEL
django_adminlte_admin-0.6.1.dist-info/metadata.json
django_adminlte_admin-0.6.1.dist-info/top_level.txt
